goblinfish/testing/pact/abcs.py
goblinfish/testing/pact/module_members.py
goblinfish/testing/pact/modules.py
goblinfish/testing/pact/pact_logging.py
goblinfish/testing/pact/projects.py
goblinfish_testing_pact-0.0.6.dist-info/licenses/LICENSE
goblinfish_testing_pact-0.0.6.dist-info/METADATA
goblinfish_testing_pact-0.0.6.dist-info/WHEEL
goblinfish_testing_pact-0.0.6.dist-info/top_level.txt
goblinfish_testing_pact-0.0.6.dist-info/RECORD
