Metadata-Version: 2.4
Name: goblinfish-testing-pact
Version: 0.0.6
Summary: Unit-testing extensions that prescribe active contract testing.
Author-email: Brian Allbee <brian.allbee+goblinfish.pact@gmail.com>
Maintainer-email: Brian Allbee <brian.allbee+goblinfish.pact@gmail.com>
License: MIT License
Project-URL: Repository, https://bitbucket.org/stonefish-software-studio/goblinfish-testing-pact
Project-URL: LinkedIn Article v.0.0.0, https://www.linkedin.com/pulse/goblinfish-testing-pact-000-prescribing-active-contract-brian-allbee-eza4c
Project-URL: LinkedIn Article: v.0.0.1, https://www.linkedin.com/pulse/goblinfish-testing-pact-001-prescribing-active-contract-brian-allbee-okrkc
Project-URL: LinkedIn Article: v.0.0.2, https://www.linkedin.com/pulse/goblinfish-testing-pact-002-prescribing-active-contract-brian-allbee-tiizc
Keywords: testing,unittest,pytest
Classifier: Programming Language :: Python :: 3.13
Classifier: Programming Language :: Python :: 3.12
Classifier: Programming Language :: Python :: 3.11
Classifier: Programming Language :: Python :: 3
Classifier: Development Status :: 3 - Alpha
Classifier: Intended Audience :: Developers
Classifier: License :: OSI Approved :: MIT License
Classifier: Natural Language :: English
Classifier: Operating System :: OS Independent
Classifier: Topic :: Software Development :: Testing
Classifier: Topic :: Software Development :: Testing :: Unit
Requires-Python: >=3.11
License-File: LICENSE
Dynamic: license-file
